{
  "project_info": {
    "project_number": "290012682072",
    "project_id": "panoramic-ai",
    "storage_bucket": "panoramic-ai.firebasestorage.app"
  },
  "client": [
    {
      "client_info": {
        "mobilesdk_app_id": "1:290012682072:android:50a3d1fae5a14ec404f72d",
        "android_client_info": {
          "package_name": "com.ardev.panoramicai"
        }
      },
      "oauth_client": [],
      "api_key": [
        {
          "current_key": "AIzaSyAQM8UmYWIMCd4gknoCICoUOUaFQexuWoc"
        }
      ],
      "services": {
        "appinvite_service": {
          "other_platform_oauth_client": []
        }
      }
    }
  ],
  "configuration_version": "1"
}